[
    {
        "id": "36602352",
        "title": "Cotton Closes the Week with Weakness",
        "url": "https://www.barchart.com/story/news/36602352/cotton-closes-the-week-with-weakness",
        "published_str_original": "Fri Dec 12, 5:12PM CST",
        "published_timestamp_utc": 1765577520,
        "summary": "Cotton futures closed the Friday session with contracts down 10 to 15 points across most front months, as March was down 10 points on the week. Crude oil futures were down 9 cents per barrel at $57.51,..."
    },
    {
        "id": "36602342",
        "title": "Hogs Posts Friday Gains",
        "url": "https://www.barchart.com/story/news/36602342/hogs-posts-friday-gains",
        "published_str_original": "Fri Dec 12, 5:12PM CST",
        "published_timestamp_utc": 1765577520,
        "summary": "Lean hog futures Posted 25 to 35 cent gains across the front months on Friday, with December down 7 cents upon expiration. February was up $2.25 this week. USDA’s national base hog price was down 41..."
    },
    {
        "id": "36602332",
        "title": "Cattle Face Pressure into the Weekend",
        "url": "https://www.barchart.com/story/news/36602332/cattle-face-pressure-into-the-weekend",
        "published_str_original": "Fri Dec 12, 5:12PM CST",
        "published_timestamp_utc": 1765577520,
        "summary": "Live cattle futures closed Friday with losses of 57 cents to $1.40, as February was $2.40 higher over the week. Cash trade was stronger this week, as most of the country was $230. Feeder cattle futures..."
    },
    {
        "id": "36602322",
        "title": "Wheat Closes with Friday Losses",
        "url": "https://www.barchart.com/story/news/36602322/wheat-closes-with-friday-losses",
        "published_str_original": "Fri Dec 12, 5:12PM CST",
        "published_timestamp_utc": 1765577520,
        "summary": "The wheat complex closed Friday with losses. Chicago SRW futures were down 4 to 5 cents in most contracts, as March was down 6 ½ cents on the week. KC HRW futures were 4 to 5 cents on Friday, with March..."
    },
    {
        "id": "36602312",
        "title": "Soybeans Continue Selling the Fact on Friday with Chinese Buying",
        "url": "https://www.barchart.com/story/news/36602312/soybeans-continue-selling-the-fact-on-friday-with-chinese-buying",
        "published_str_original": "Fri Dec 12, 5:12PM CST",
        "published_timestamp_utc": 1765577520,
        "summary": "Soybeans fell lower into the weekend, with contracts 15 to 17 cents lower on Friday. Weekly losses were 28 cents in the January contract. The cmdtyView national average Cash Bean price was 17 cents lower..."
    },
    {
        "id": "36602302",
        "title": "Corn Falls to Close the Week",
        "url": "https://www.barchart.com/story/news/36602302/corn-falls-to-close-the-week",
        "published_str_original": "Fri Dec 12, 5:12PM CST",
        "published_timestamp_utc": 1765577520,
        "summary": "Corn futures closed the Friday session with contracts down 4 to 6 cents across most nearbys, as December expired. March settled the week with a 4 cent loss. The CmdtyView national average Cash Corn price..."
    },
    {
        "id": "36599911",
        "title": "Dollar Finds Support from Higher T-Note Yields",
        "url": "https://www.barchart.com/story/news/36599911/dollar-finds-support-from-higher-t-note-yields",
        "published_str_original": "Fri Dec 12, 2:34PM CST",
        "published_timestamp_utc": 1765568040,
        "summary": "The dollar index (DXY00 ) on Friday rose by +0.02%.  The dollar moved slightly higher on Friday, as hawkish Fed comments boosted T-note yields.  Chicago Fed President Austan Goolsbee said that, given higher..."
    },
    {
        "id": "36599447",
        "title": "Dollar Strength and Stock Market Weakness Undercut Crude Oil Prices",
        "url": "https://www.barchart.com/story/news/36599447/dollar-strength-and-stock-market-weakness-undercut-crude-oil-prices",
        "published_str_original": "Fri Dec 12, 2:18PM CST",
        "published_timestamp_utc": 1765567080,
        "summary": "January WTI crude oil (CLF26 ) on Friday closed down -0.16 (-0.28%), and January RBOB gasoline (RBF26 ) closed down -0.0077 (-0.44%). Crude oil and gasoline prices moved lower on Friday, with gasoline..."
    },
    {
        "id": "36599417",
        "title": "Nat-Gas Prices Hammered by Forecasts for Above-Average US Temps",
        "url": "https://www.barchart.com/story/news/36599417/nat-gas-prices-hammered-by-forecasts-for-above-average-us-temps",
        "published_str_original": "Fri Dec 12, 2:17PM CST",
        "published_timestamp_utc": 1765567020,
        "summary": "January Nymex natural gas (NGF26 ) on Friday closed down by -0.118 (-2.79%). Jan nat-gas prices extended this week's sharp sell-off on Friday, sinking to a 6-week low.   US weather forecasts calling for..."
    },
    {
        "id": "36599033",
        "title": "Sugar Prices Climb as the Brazilian Real Strengthens",
        "url": "https://www.barchart.com/story/news/36599033/sugar-prices-climb-as-the-brazilian-real-strengthens",
        "published_str_original": "Fri Dec 12, 1:33PM CST",
        "published_timestamp_utc": 1765564380,
        "summary": "March NY world sugar #11 (SBH26 ) on Friday closed up +0.25 (+1.68%), and March London ICE white sugar #5 (SWH26 ) closed up +5.20 (+1.23%). Sugar prices settled sharply higher on Friday, with NY sugar..."
    },
    {
        "id": "36598981",
        "title": "Cocoa Prices Settle Mixed on Currency Fluctuations",
        "url": "https://www.barchart.com/story/news/36598981/cocoa-prices-settle-mixed-on-currency-fluctuations",
        "published_str_original": "Fri Dec 12, 1:31PM CST",
        "published_timestamp_utc": 1765564260,
        "summary": "March ICE NY cocoa (CCH26 ) on Friday closed down -9 (-0.14%), and March ICE London cocoa #7 (CAH26 ) closed up +58 (+1.29%). Cocoa prices settled mixed on Friday, consolidating this week's gains.  NY..."
    },
    {
        "id": "36598911",
        "title": "Coffee Prices Retreat on the Outlook for Ample Supplies",
        "url": "https://www.barchart.com/story/news/36598911/coffee-prices-retreat-on-the-outlook-for-ample-supplies",
        "published_str_original": "Fri Dec 12, 1:25PM CST",
        "published_timestamp_utc": 1765563900,
        "summary": "March arabica coffee (KCH26 ) on Friday closed down -6.90 (-1.83%), and January ICE robusta coffee (RMF26 ) closed down -84 (-2.00%). Coffee prices fell sharply on Friday, with robusta posting a 2.5-month..."
    },
    {
        "id": "36597778",
        "title": "Cotton Slipping at Friday’s Midday",
        "url": "https://www.barchart.com/story/news/36597778/cotton-slipping-at-fridays-midday",
        "published_str_original": "Fri Dec 12, 12:15PM CST",
        "published_timestamp_utc": 1765559700,
        "summary": "Cotton futures are back to slightly weaker trade on Friday, with contracts down 2 to 5 points in the nearbys. Crude oil futures are up 5 cents per barrel at $57.64, with the US dollar index $0.21 lower..."
    },
    {
        "id": "36597734",
        "title": "Soybeans Falling on Friday Despite Chinese Business Trickling In",
        "url": "https://www.barchart.com/story/news/36597734/soybeans-falling-on-friday-despite-chinese-business-trickling-in",
        "published_str_original": "Fri Dec 12, 12:15PM CST",
        "published_timestamp_utc": 1765559700,
        "summary": "Soybeans are falling 12 to 13 cents in the nearbys on Friday. The cmdtyView national average Cash Bean price is 11 3/4 cents lower at $10.10 3/4. Soymeal futures are $1.70 higher, with Soy Oil futures..."
    },
    {
        "id": "36597015",
        "title": "Brazilian Real Strength Spurs Short Covering in Sugar Futures",
        "url": "https://www.barchart.com/story/news/36597015/brazilian-real-strength-spurs-short-covering-in-sugar-futures",
        "published_str_original": "Fri Dec 12, 11:34AM CST",
        "published_timestamp_utc": 1765557240,
        "summary": "March NY world sugar #11 (SBH26 ) today is up +0.22 (+1.48%), and March London ICE white sugar #5 (SWH26 ) is up +4.30 (+1.01%). Sugar prices are moving sharply higher today, with NY sugar posting a 2-week..."
    },
    {
        "id": "36596771",
        "title": "Cocoa Prices Consolidate Recent Gains",
        "url": "https://www.barchart.com/story/news/36596771/cocoa-prices-consolidate-recent-gains",
        "published_str_original": "Fri Dec 12, 11:15AM CST",
        "published_timestamp_utc": 1765556100,
        "summary": "March ICE NY cocoa (CCH26 ) today is up +7 (+0.11%), and March ICE London cocoa #7 (CAH26 ) is up +68 (+0.51%). Cocoa prices are moving higher today, consolidating this week's gains.   Cocoa prices rallied..."
    },
    {
        "id": "36596312",
        "title": "Coffee Prices Slip as Supply Concerns Ease",
        "url": "https://www.barchart.com/story/news/36596312/coffee-prices-slip-as-supply-concerns-ease",
        "published_str_original": "Fri Dec 12, 10:51AM CST",
        "published_timestamp_utc": 1765554660,
        "summary": "March arabica coffee (KCH26 ) today is down -7.50 (-1.99%), and January ICE robusta coffee (RMF26 ) is down -78 (-1.85%). Coffee prices are sharply lower today, with robusta falling to a 2.5-month low...."
    },
    {
        "id": "36596114",
        "title": "Crude Oil Prices Slip on Dollar Strength and Oil Glut Concerns",
        "url": "https://www.barchart.com/story/news/36596114/crude-oil-prices-slip-on-dollar-strength-and-oil-glut-concerns",
        "published_str_original": "Fri Dec 12, 10:36AM CST",
        "published_timestamp_utc": 1765553760,
        "summary": "January WTI crude oil (CLF26 ) today is down -0.32 (-0.56%), and January RBOB gasoline (RBF26 ) closed down -0.0118 (-0.67%). Crude oil and gasoline prices are falling today, with gasoline posting a 4.75-year..."
    },
    {
        "id": "36595761",
        "title": "Will Cocoa Remain Above the Critical Long-Term Technical Support?",
        "url": "https://www.barchart.com/story/news/36595761/will-cocoa-remain-above-the-critical-long-term-technical-support",
        "published_str_original": "Fri Dec 12, 10:13AM CST",
        "published_timestamp_utc": 1765552380,
        "summary": "After reaching a record high of $12,931 per ton in December 2024, nearby ICE cocoa futures prices have more than halved, trading around the $5,500 level in late 2025. Cocoa remains in a bearish trend in..."
    },
    {
        "id": "36595197",
        "title": "Here Are the Levels to Watch as Cattle Prices Keep Moving Higher",
        "url": "https://www.barchart.com/story/news/36595197/here-are-the-levels-to-watch-as-cattle-prices-keep-moving-higher",
        "published_str_original": "Fri Dec 12, 9:38AM CST",
        "published_timestamp_utc": 1765550280,
        "summary": "February live cattle futures present a buying opportunity on more price strength."
    },
    {
        "id": "36594231",
        "title": "Is NRG Energy Stock Outperforming the Dow?",
        "url": "https://www.barchart.com/story/news/36594231/is-nrg-energy-stock-outperforming-the-dow",
        "published_str_original": "Fri Dec 12, 8:45AM CST",
        "published_timestamp_utc": 1765547100,
        "summary": "NRG Energy has outperformed the Dow over the past year, and analysts are moderately optimistic about the stock’s prospects."
    },
    {
        "id": "36592690",
        "title": "Cattle Look to Friday Trade Following Cash Strength",
        "url": "https://www.barchart.com/story/news/36592690/cattle-look-to-friday-trade-following-cash-strength",
        "published_str_original": "Fri Dec 12, 7:39AM CST",
        "published_timestamp_utc": 1765543140,
        "summary": "Live cattle futures closed the Thursday session with contracts $2.30 to $3.57 higher, following the rallying cash market. There were no new deliveries on Thursday. Cash trade picked up on Thursday with..."
    },
    {
        "id": "36592657",
        "title": "Corn Starting Friday with Slight Losses",
        "url": "https://www.barchart.com/story/news/36592657/corn-starting-friday-with-slight-losses",
        "published_str_original": "Fri Dec 12, 7:39AM CST",
        "published_timestamp_utc": 1765543140,
        "summary": "Corn price action is down 1 to 2 cents in the front months on Friday morning. Futures posted higher Thursday trade, with contracts up fractionally to 2 ½ cents in the nearby contracts. December futures..."
    },
    {
        "id": "36592305",
        "title": "What Does the Latest Rate Cut Mean for Commodity Investments?",
        "url": "https://www.barchart.com/story/news/36592305/what-does-the-latest-rate-cut-mean-for-commodity-investments",
        "published_str_original": "Fri Dec 12, 7:19AM CST",
        "published_timestamp_utc": 1765541940,
        "summary": "After the latest rate cut by the US FOMC and ahead of the turn of the calendar page to 2026, has the long-term investment outlook for the commodity complex changed?"
    },
    {
        "id": "36588237",
        "title": "How Is Everest Group's Stock Performance Compared to Other Insurance Stocks?",
        "url": "https://www.barchart.com/story/news/36588237/how-is-everest-group-s-stock-performance-compared-to-other-insurance-stocks",
        "published_str_original": "Fri Dec 12, 2:54AM CST",
        "published_timestamp_utc": 1765526040,
        "summary": "Everest Group has notably underperformed compared to other insurance stocks over the past year, yet analysts remain optimistic about the stock’s prospects."
    }
]