[
    {
        "id": "36895069",
        "title": "Cotton Rally on Monday",
        "url": "https://www.barchart.com/story/news/36895069/cotton-rally-on-monday",
        "published_str_original": "Mon Jan 5, 5:12PM CST",
        "published_timestamp_utc": 1767651120,
        "summary": "Cotton futures posted gains for 55 to 64 points in the nearbys on Monday to rally out of the holiday slowed weeks. Crude oil futures were back up $1.08 per barrel at $58.34. The US dollar index was down..."
    },
    {
        "id": "36895059",
        "title": "Hogs Rally on Monday",
        "url": "https://www.barchart.com/story/news/36895059/hogs-rally-on-monday",
        "published_str_original": "Mon Jan 5, 5:12PM CST",
        "published_timestamp_utc": 1767651120,
        "summary": "Lean hog futures posted gains of $2.05 to $2.50 gains in the front months on Monday. USDA’s national base hog price was reported at $66.36 on Monday afternoon. The CME Lean Hog Index was back down 41..."
    },
    {
        "id": "36895049",
        "title": "Cattle Close Mostly Higher on Monday",
        "url": "https://www.barchart.com/story/news/36895049/cattle-close-mostly-higher-on-monday",
        "published_str_original": "Mon Jan 5, 5:12PM CST",
        "published_timestamp_utc": 1767651120,
        "summary": "Live cattle futures closed with mostly higher action, up 82 cents to $1.25, as the exception was February, down 12 cents. Cash trade from last week settled in at $232-233 across the country. Feeder cattle..."
    },
    {
        "id": "36895039",
        "title": "Wheat Closes with Strength on Monday",
        "url": "https://www.barchart.com/story/news/36895039/wheat-closes-with-strength-on-monday",
        "published_str_original": "Mon Jan 5, 5:12PM CST",
        "published_timestamp_utc": 1767651120,
        "summary": "The wheat complex posted gains across the three exchanges to close out the Monday session. Chicago SRW futures closed with 5 to 6 cent gains. KC HRW futures were 5 to 6 cents in the green at the final..."
    },
    {
        "id": "36895029",
        "title": "Soybeans Post Double Digit Gains on Monday",
        "url": "https://www.barchart.com/story/news/36895029/soybeans-post-double-digit-gains-on-monday",
        "published_str_original": "Mon Jan 5, 5:12PM CST",
        "published_timestamp_utc": 1767651120,
        "summary": "Soybeans were in rally mode as traders came back from the thin holiday markets, with futures closing up 15 to 18 cents. There were another 401 deliveries against January soybeans issued on Friday evening...."
    },
    {
        "id": "36895019",
        "title": "Corn Rallies Back on Monday",
        "url": "https://www.barchart.com/story/news/36895019/corn-rallies-back-on-monday",
        "published_str_original": "Mon Jan 5, 5:12PM CST",
        "published_timestamp_utc": 1767651120,
        "summary": "Corn futures came out of the holiday slowed weeks with gains across the board. Front months were up 6 to 7 cents to lead the charge. The CmdtyView national average Cash Corn price was up 7 1/2 cents at..."
    },
    {
        "id": "36892139",
        "title": "Dollar Pulls Back as US Manufacturing Activity Contracts",
        "url": "https://www.barchart.com/story/news/36892139/dollar-pulls-back-as-us-manufacturing-activity-contracts",
        "published_str_original": "Mon Jan 5, 2:32PM CST",
        "published_timestamp_utc": 1767641520,
        "summary": "The dollar index (DXY00 ) fell from a 3-week high on Monday and finished down by -0.16%.  The dollar retreated on Monday after the US Dec ISM manufacturing index unexpectedly contracted by the most in..."
    },
    {
        "id": "36891979",
        "title": "Halliburton Stock Just Pushed into Overbought Territory Amid Venezuela Tumult. Is There Still Time to Buy HAL?",
        "url": "https://www.barchart.com/story/news/36891979/halliburton-stock-just-pushed-into-overbought-territory-amid-venezuela-tumult-is-there-still-time-to-buy-hal",
        "published_str_original": "Mon Jan 5, 2:27PM CST",
        "published_timestamp_utc": 1767641220,
        "summary": "Halliburton stock rallies as the U.S. launches a military operation in Venezuela. Here’s what could drive HAL shares higher in 2026."
    },
    {
        "id": "36891909",
        "title": "Crude Rallies on Rising Geopolitical Risks",
        "url": "https://www.barchart.com/story/news/36891909/crude-rallies-on-rising-geopolitical-risks",
        "published_str_original": "Mon Jan 5, 2:18PM CST",
        "published_timestamp_utc": 1767640680,
        "summary": "February WTI crude oil (CLG26 ) on Monday closed up +1.00 (+1.74%), and February RBOB gasoline (RBG26 ) closed up +0.0218 (+1.28%). Crude oil and gasoline prices recovered from early losses on Monday and..."
    },
    {
        "id": "36891878",
        "title": "Above-Normal US Temps Weigh on Nat-Gas Prices",
        "url": "https://www.barchart.com/story/news/36891878/above-normal-us-temps-weigh-on-nat-gas-prices",
        "published_str_original": "Mon Jan 5, 2:17PM CST",
        "published_timestamp_utc": 1767640620,
        "summary": "February Nymex natural gas (NGG26 ) on Monday closed down -0.095 (-2.63%), Feb nat-gas prices fell to a 2.25-month low on the nearest futures chart on Monday and settled sharply lower.  Weather forecasts..."
    },
    {
        "id": "36891688",
        "title": "Cattle Bulls Are Hitting the Gas in 2026: What to Watch, and Why Grains and Hogs Are Down",
        "url": "https://www.barchart.com/story/news/36891688/cattle-bulls-are-hitting-the-gas-in-2026-what-to-watch-and-why-grains-and-hogs-are-down",
        "published_str_original": "Mon Jan 5, 2:00PM CST",
        "published_timestamp_utc": 1767639600,
        "summary": "Traders will be watching U.S.-China trade relations, a Russia-Ukraine peace deal, and new cases of the new world screwworm, among other catalysts as the new year kicks off."
    },
    {
        "id": "36891453",
        "title": "2025 Wasn’t an Easy Year for Tesla Stock, but Baird Says It’s a ‘Core Holding’ for 2026 Anyways",
        "url": "https://www.barchart.com/story/news/36891453/2025-wasnt-an-easy-year-for-tesla-stock-but-baird-says-its-a-core-holding-for-2026-anyways",
        "published_str_original": "Mon Jan 5, 1:39PM CST",
        "published_timestamp_utc": 1767638340,
        "summary": "Tesla enters 2026 as a high‑beta “prove‑it” story, with record free cash flow and new energy and AI levers offset by falling deliveries, a rich multiple, and a consensus \"Hold\" rating."
    },
    {
        "id": "36891323",
        "title": "Sugar Prices Settle Higher as Brazilian Real Strength Spurs Short Covering",
        "url": "https://www.barchart.com/story/news/36891323/sugar-prices-settle-higher-as-brazilian-real-strength-spurs-short-covering",
        "published_str_original": "Mon Jan 5, 1:25PM CST",
        "published_timestamp_utc": 1767637500,
        "summary": "March NY world sugar #11 (SBH26 ) on Monday closed up +0.13 (+0.89%).  March London ICE white sugar #5 (SWH26 ) closed up +2.50 (+0.60%). Sugar prices rose on Monday as strength in the Brazilian real prompted..."
    },
    {
        "id": "36891268",
        "title": "Smaller Cocoa Deliveries to Ivory Coast Ports Boost Cocoa Prices",
        "url": "https://www.barchart.com/story/news/36891268/smaller-cocoa-deliveries-to-ivory-coast-ports-boost-cocoa-prices",
        "published_str_original": "Mon Jan 5, 1:21PM CST",
        "published_timestamp_utc": 1767637260,
        "summary": "March ICE NY cocoa (CCH26 ) on Monday closed up +206 (+3.51%).  March ICE London cocoa #7 (CAH26 ) closed up +109 (+2.57%). Cocoa prices rallied sharply on Monday on signs of smaller cocoa supplies from..."
    },
    {
        "id": "36891239",
        "title": "Arabica Coffee Settles Higher on Below-Normal Rains in Brazil",
        "url": "https://www.barchart.com/story/news/36891239/arabica-coffee-settles-higher-on-below-normal-rains-in-brazil",
        "published_str_original": "Mon Jan 5, 1:20PM CST",
        "published_timestamp_utc": 1767637200,
        "summary": "March arabica coffee (KCH26 ) on Monday closed up +2.05 (+0.57%).  March ICE robusta coffee (RMH26 ) closed down -36 (-0.91%). Coffee prices settled mixed on Monday, with robusta falling to a 1-week low...."
    },
    {
        "id": "36890065",
        "title": "Cotton Rallying Higher on Monday",
        "url": "https://www.barchart.com/story/news/36890065/cotton-rallying-higher-on-monday",
        "published_str_original": "Mon Jan 5, 12:18PM CST",
        "published_timestamp_utc": 1767633480,
        "summary": "Cotton futures are showing 63 to 68 point gains in the nearbys on Monday. Crude oil futures are back up 92 cents per barrel at $58.24, following the US capture of Venezuela President Maduro over the weekend...."
    },
    {
        "id": "36890055",
        "title": "Hogs Starting Monday with Gains",
        "url": "https://www.barchart.com/story/news/36890055/hogs-starting-monday-with-gains",
        "published_str_original": "Mon Jan 5, 12:18PM CST",
        "published_timestamp_utc": 1767633480,
        "summary": "Lean hog futures are showing $2.25 to $2.60 gains so far on Monday. USDA’s national base hog price was not reported on Monday morning due to thin volume. The CME Lean Hog Index was back down 41 cents..."
    },
    {
        "id": "36890045",
        "title": "Cattle Extending Gains to Monday’s Midday",
        "url": "https://www.barchart.com/story/news/36890045/cattle-extending-gains-to-mondays-midday",
        "published_str_original": "Mon Jan 5, 12:18PM CST",
        "published_timestamp_utc": 1767633480,
        "summary": "Live cattle futures are up 20 cents in the nearby February contracts, with other months $1 to $1.50 higher. Cash trade from last week settled in at $232-233 across the country. Feeder cattle futures are..."
    },
    {
        "id": "36890035",
        "title": "Wheat Trading with Monday Midday Gains",
        "url": "https://www.barchart.com/story/news/36890035/wheat-trading-with-monday-midday-gains",
        "published_str_original": "Mon Jan 5, 12:18PM CST",
        "published_timestamp_utc": 1767633480,
        "summary": "The wheat complex are trading with gains across the three markets in Monday. Chicago SRW futures are 5 to 6 cents higher at midday. KC HRW futures are 8 to 9 cents in the green at midday. MPLS spring wheat..."
    },
    {
        "id": "36890025",
        "title": "Soybeans Posting Monday AM Rally",
        "url": "https://www.barchart.com/story/news/36890025/soybeans-posting-monday-am-rally",
        "published_str_original": "Mon Jan 5, 12:18PM CST",
        "published_timestamp_utc": 1767633480,
        "summary": "Soybeans are in rally mode as traders come back from the thin holiday markets, with futures up 15 to 18 ¼ centas. There were another 401 deliveries against January soybeans issued on Friday evening. The..."
    },
    {
        "id": "36890015",
        "title": "Corn Rallying on Monday",
        "url": "https://www.barchart.com/story/news/36890015/corn-rallying-on-monday",
        "published_str_original": "Mon Jan 5, 12:18PM CST",
        "published_timestamp_utc": 1767633480,
        "summary": "Corn futures are rallying out of the holiday weeks, with contracts up 6 to 7 ¼ cents across the nearbys. The CmdtyView national average Cash Corn price was up 7 1/4 cents at $4.06 1/2.  USDA tallied corn..."
    },
    {
        "id": "36889245",
        "title": "Why ConocoPhillips Is One of the Top Oil Stocks to Buy After Venezuela",
        "url": "https://www.barchart.com/story/news/36889245/why-conocophillips-is-one-of-the-top-oil-stocks-to-buy-after-venezuela",
        "published_str_original": "Mon Jan 5, 11:29AM CST",
        "published_timestamp_utc": 1767630540,
        "summary": "ConocoPhillips emerges as a compelling investment amid the expected revival of Venezuela’s oil sector, blending its arbitration leverage, heavy crude expertise, and solid fundamentals for long-term gains...."
    },
    {
        "id": "36889232",
        "title": "Chevron, ConocoPhillips, and Gold: Your Critical Watchlist After the U.S.–Venezuela Oil Market Shock",
        "url": "https://www.barchart.com/story/news/36889232/chevron-conocophillips-and-gold-your-critical-watchlist-after-the-u-s-venezuela-oil-market-shock",
        "published_str_original": "Mon Jan 5, 11:28AM CST",
        "published_timestamp_utc": 1767630480,
        "summary": "Markets are reacting to what could become the largest geopolitical energy shift in decades."
    },
    {
        "id": "36889208",
        "title": "Sugar Prices Push Higher on Strength in the Brazilian Real",
        "url": "https://www.barchart.com/story/news/36889208/sugar-prices-push-higher-on-strength-in-the-brazilian-real",
        "published_str_original": "Mon Jan 5, 11:27AM CST",
        "published_timestamp_utc": 1767630420,
        "summary": "March NY world sugar #11 (SBH26 ) today is up +0.15 (+1.03%).  March London ICE white sugar #5 (SWH26 ) is up +2.50 (+0.60%). Sugar prices are moving higher today as strength in the Brazilian real has..."
    },
    {
        "id": "36889009",
        "title": "Cocoa Prices Gain on Smaller Deliveries of Cocoa to Ivory Coast Ports",
        "url": "https://www.barchart.com/story/news/36889009/cocoa-prices-gain-on-smaller-deliveries-of-cocoa-to-ivory-coast-ports",
        "published_str_original": "Mon Jan 5, 11:14AM CST",
        "published_timestamp_utc": 1767629640,
        "summary": "March ICE NY cocoa (CCH26 ) today is up +181 (+3.08%).  March ICE London cocoa #7 (CAH26 ) is up +109 (+2.57%). Cocoa prices are climbing today on signs of smaller cocoa supplies from the Ivory Coast...."
    },
    {
        "id": "36888699",
        "title": "Coffee Prices Mixed on Slack Rain in Brazil and Higher Vietnam Coffee Exports",
        "url": "https://www.barchart.com/story/news/36888699/coffee-prices-mixed-on-slack-rain-in-brazil-and-higher-vietnam-coffee-exports",
        "published_str_original": "Mon Jan 5, 11:00AM CST",
        "published_timestamp_utc": 1767628800,
        "summary": "March arabica coffee (KCH26 ) today is up +0.60 (+0.17%). March ICE robusta coffee (RMH26 ) is down -100 (-2.53%). Coffee prices are mixed today, with robusta falling to a 1-week low.  Below-average rainfall..."
    },
    {
        "id": "36888438",
        "title": "Crude Rallies as OPEC+ Keeps Output Levels Unchanged in Q1",
        "url": "https://www.barchart.com/story/news/36888438/crude-rallies-as-opec-keeps-output-levels-unchanged-in-q1",
        "published_str_original": "Mon Jan 5, 10:45AM CST",
        "published_timestamp_utc": 1767627900,
        "summary": "February WTI crude oil (CLG26 ) today is up +0.88 (+1.54%), and February RBOB gasoline (RBG26 ) is up +0.0192 (+1.13%). Crude oil and gasoline prices recovered from early losses today and are sharply higher..."
    },
    {
        "id": "36887656",
        "title": "Your Coffee Is Getting Cold: 1 Trade to Make as Arabica Prices Stumble",
        "url": "https://www.barchart.com/story/news/36887656/your-coffee-is-getting-cold-1-trade-to-make-as-arabica-prices-stumble",
        "published_str_original": "Mon Jan 5, 9:55AM CST",
        "published_timestamp_utc": 1767624900,
        "summary": "March coffee futures present a selling opportunity on more price weakness."
    },
    {
        "id": "36887276",
        "title": "Dollar Rallies and Precious Metals Surge on Geopolitical Risks",
        "url": "https://www.barchart.com/story/news/36887276/dollar-rallies-and-precious-metals-surge-on-geopolitical-risks",
        "published_str_original": "Mon Jan 5, 9:26AM CST",
        "published_timestamp_utc": 1767623160,
        "summary": "The dollar index (DXY00 ) rose to a 3-week high today and is up by +0.15%.  Escalation of geopolitical risks in Venezuela boosted safe-haven demand for the dollar after the US captured Venezuelan president..."
    },
    {
        "id": "36884561",
        "title": "Cotton Starting Monday with a Rally Back",
        "url": "https://www.barchart.com/story/news/36884561/cotton-starting-monday-with-a-rally-back",
        "published_str_original": "Mon Jan 5, 7:26AM CST",
        "published_timestamp_utc": 1767615960,
        "summary": "Cotton price action is up 35 to 46 points so far on Monday morning. Futures closed the Friday session with weakness, as contracts were down 11 to 26 points, with March slipping 48 points over the short..."
    },
    {
        "id": "36884540",
        "title": "Cattle Look to Fresh Week of Trade Following Last Week’s Rally",
        "url": "https://www.barchart.com/story/news/36884540/cattle-look-to-fresh-week-of-trade-following-last-weeks-rally",
        "published_str_original": "Mon Jan 5, 7:26AM CST",
        "published_timestamp_utc": 1767615960,
        "summary": "Live cattle futures were held up by the rallying cash market, with contracts up $3.50 to $4.40 in the front months. February was up $6.35 on the week. Open interest in Friday was up 4,477 contracts. Cash..."
    },
    {
        "id": "36884530",
        "title": "Wheat Posting Modest Monday AM Gains",
        "url": "https://www.barchart.com/story/news/36884530/wheat-posting-modest-monday-am-gains",
        "published_str_original": "Mon Jan 5, 7:26AM CST",
        "published_timestamp_utc": 1767615960,
        "summary": "Wheat is showing slight fractional to 3 cent gains across the three exchanges so far on Monday morning. The wheat complex posted mixed trade on Friday as the new year kicked off. Chicago SRW futures were..."
    },
    {
        "id": "36881187",
        "title": "How Did the 3 Kings of Commodities React to Weekend Developments?",
        "url": "https://www.barchart.com/story/news/36881187/how-did-the-3-kings-of-commodities-react-to-weekend-developments",
        "published_str_original": "Mon Jan 5, 5:15AM CST",
        "published_timestamp_utc": 1767608100,
        "summary": "The 3 Kings of Commodities (Gold, Crude Oil, and Corn) showed different reactions to the US actions in Venezuela over the weekend."
    },
    {
        "id": "36880037",
        "title": "Phillips 66 Earnings Preview: What to Expect",
        "url": "https://www.barchart.com/story/news/36880037/phillips-66-earnings-preview-what-to-expect",
        "published_str_original": "Mon Jan 5, 3:15AM CST",
        "published_timestamp_utc": 1767600900,
        "summary": "Phillips 66 will release its fourth-quarter earnings next month, and analysts anticipate a robust bottom-line growth."
    }
]